aws_mfa.py
aws_mfa_cli-0.0.5.dist-info/LICENSE
aws_mfa_cli-0.0.5.dist-info/METADATA
aws_mfa_cli-0.0.5.dist-info/WHEEL
aws_mfa_cli-0.0.5.dist-info/entry_points.txt
aws_mfa_cli-0.0.5.dist-info/top_level.txt
aws_mfa_cli-0.0.5.dist-info/RECORD
