Metadata-Version: 2.1
Name: aws-mfa-cli
Version: 0.0.5
Summary: CLI tool for managing AWS MFA credentials
Home-page: https://github.com/marlanperumal/aws-mfa-cli
Author: Marlan Perumal
Author-email: marlan.perumal@gmail.com
License: UNKNOWN
Platform: UNKNOWN
Classifier: Programming Language :: Python :: 3
Classifier: License :: OSI Approved :: MIT License
Classifier: Operating System :: OS Independent
Requires-Python: >=3.6
Requires-Dist: Click
